<?xml version="1.0" encoding="UTF-8" standalone="yes"?>
<ns4:Register.Afa xmlns:ns2="urn:publicid:-:DGTAXUD:GENERAL:ENVELOPE:1.0" xmlns:ns3="urn:publicid:-:DGTAXUD:GENERAL:REFERENCESET:1.0" xmlns:ns4="urn:publicid:-:DGTAXUD:COPIS:MESSAGE:1.0">
    <ns4:Afa>
        <ns4:Afa.Id>IT20180001</ns4:Afa.Id>
        <ns4:App.Type>NAFA</ns4:App.Type>
        <ns4:Reception.Date>2018-01-12</ns4:Reception.Date>
        <ns4:Language>IT</ns4:Language>
        <ns4:Exofficio>0</ns4:Exofficio>
    </ns4:Afa>
    <ns4:Applicant>
        <ns4:Uuid>60e4106381ea4b95b878b24500ca8e53</ns4:Uuid>
        <ns4:Name>asd</ns4:Name>
        <ns4:Address>asd</ns4:Address>
        <ns4:Town>asd</ns4:Town>
        <ns4:CountryCode>AD</ns4:CountryCode>
        <ns4:National.Nr>03829720378</ns4:National.Nr>
        <ns4:Mail>asd@asd.asd</ns4:Mail>
        <ns4:Status>CPR</ns4:Status>
    </ns4:Applicant>
    <ns4:Ms.Applicable>
        <ns4:CountryCode>IT</ns4:CountryCode>
        <ns4:Consignment.Proc>0</ns4:Consignment.Proc>
        <ns4:ContactPerson>
            <ns4:Uuid>74710c1aad2641e3ad987e5ca97040b9</ns4:Uuid>
            <ns4:Contact.Type>BTH</ns4:Contact.Type>
            <ns4:Name>asd</ns4:Name>
            <ns4:Address>asd</ns4:Address>
            <ns4:Town>asd</ns4:Town>
            <ns4:CountryCode>AO</ns4:CountryCode>
            <ns4:Phone>+398448</ns4:Phone>
            <ns4:Mobile>+394888</ns4:Mobile>
            <ns4:Mail>asd@asd.ad</ns4:Mail>
        </ns4:ContactPerson>
    </ns4:Ms.Applicable>
    <ns4:Ipr>
        <ns4:Uuid>ddfc0b7fb96f4490bacefe260160a94d</ns4:Uuid>
        <ns4:Id>11003864</ns4:Id>
        <ns4:Ipr.Type>UPT</ns4:Ipr.Type>
        <ns4:Ipr.Number>4578875785</ns4:Ipr.Number>
        <ns4:Fill.Date>2018-01-11</ns4:Fill.Date>
        <ns4:Expiry.Date>2018-01-31</ns4:Expiry.Date>
        <ns4:Trademark>sdfgbstdhgh</ns4:Trademark>
        <ns4:Registered>0</ns4:Registered>
        <ns4:Related.Person>
            <ns4:Uuid>159bb8f35dcf4c11a41ef831a0c37824</ns4:Uuid>
            <ns4:Person.Type>AU</ns4:Person.Type>
            <ns4:Name>dsfg gdsw</ns4:Name>
        </ns4:Related.Person>
    </ns4:Ipr>
    <ns4:Good_Detail>
        <ns4:Uuid>e7bdb83c679940ca8f1ae166842c3736</ns4:Uuid>
        <ns4:Id>83456961</ns4:Id>
        <ns4:Item.Type>AUTH</ns4:Item.Type>
        <ns4:Description>gfsdgfsfsdd</ns4:Description>
        <ns4:Customs.Value>1</ns4:Customs.Value>
        <ns4:National.Value>11</ns4:National.Value>
        <ns4:Community.Value>1</ns4:Community.Value>
        <ns4:Confidential>0</ns4:Confidential>
        <ns4:Associated.Ipr>
            <ns4:Uuid>6ecdf391b9b74afe82463452c328c0fb</ns4:Uuid>
            <ns4:Ipr.Id>11003864</ns4:Ipr.Id>
        </ns4:Associated.Ipr>
        <ns4:Production.Place>
            <ns4:Uuid>d3f91cabd6114a13871a0dfdebc33bd0</ns4:Uuid>
            <ns4:CountryCode>AF</ns4:CountryCode>
            <ns4:Confidential>0</ns4:Confidential>
        </ns4:Production.Place>
        <ns4:Involved.Company>
            <ns4:Uuid>45132d9a9ef84e9e9c16a68aa5bf64c4</ns4:Uuid>
            <ns4:Tin>1</ns4:Tin>
            <ns4:Role>DIS</ns4:Role>
            <ns4:Confidential>0</ns4:Confidential>
            <ns4:Name>sdgfg</ns4:Name>
            <ns4:CountryCode>DZ</ns4:CountryCode>
            <ns4:Language>IT</ns4:Language>
        </ns4:Involved.Company>
        <ns4:Trader>
            <ns4:Uuid>3dd7eb0282f34b0ba633b60b610d6f5d</ns4:Uuid>
            <ns4:Tin>1</ns4:Tin>
        </ns4:Trader>
    </ns4:Good_Detail>
</ns4:Register.Afa>
